[{
  "title": "Development",
  "topics": [{
    "title": "Local development environment"
  }, {
    "title": "Local vs. Cloud development environment"
  }, {
    "title": "Development in AWS accounts"
  }, {
    "title": "Development tools (Git, Docker, etc.)"
  }]
}, {
  "title": "Testing",
  "topics": [{
    "title": "Fundamentals of Testing (small tests, easy to maintain, focused, fast)"
  }, {
    "title": "Pros/cons of metrics (coverage)"
  }, {
    "title": "Importance of deterministic/non-flaky tests"
  }, {
    "title": "Picking the correct abstraction (unit/integration/canary)"
  }, {
    "title": "Unit testing"
  }, {
    "title": "Integration testing"
  }, {
    "title": "Browser testing"
  }, {
    "title": "Mobile testing"
  }, {
    "title": "Code Coverage"
  }, {
    "title": "Test automation"
  }, {
    "title": "What are canary tests"
  }]
}, {
  "title": "Infrastructure",
  "topics": [{
    "title": "Provisioning"
  }, {
    "title": "Maintenance (e.g. host patching, benefits of serverless)"
  }, {
    "title": "Infrastructure as Code (CDK)"
  }, {
    "title": "CI/CD for infrastructure"
  }, {
    "title": "AWS Accounts / Organisations / SSO (service separation)"
  }, {
    "title": "Cost management"
  }]
}, {
  "title": "Deployment",
  "topics": [{
    "title": "CI/CD"
  }, {
    "title": "Pipelines"
  }, {
    "title": "Stages"
  }, {
    "title": "Build processes/systems"
  }, {
    "title": "Approval steps"
  }, {
    "title": "Rollbacks (automatic)"
  }, {
    "title": "Testing in production"
  }]
}, {
  "title": "Operations",
  "topics": [{
    "title": "Operational dashboards"
  }, {
    "title": "Other resources to monitor (e.g. Twitter, AWS Status)"
  }, {
    "title": "Monitoring"
  }, {
    "title": "Alarming"
  }, {
    "title": "Canaries"
  }, {
    "title": "Paging"
  }, {
    "title": "Automatic Rollbacks"
  }, {
    "title": "Run-books"
  }, {
    "title": "Load testing"
  }, {
    "title": "Error logging (+gotchas e.g. post body in logs)"
  }, {
    "title": "Game Days"
  }]
}, {
  "title": "Serverless",
  "topics": [{
    "title": "Lambda"
  }, {
    "title": "API Gateway"
  }, {
    "title": "DynamoDB"
  }, {
    "title": "S3"
  }, {
    "title": "SES"
  }, {
    "title": "CloudFront"
  }]
}, {
  "title": "Backend",
  "topics": [{
    "title": "Dynamic rendering"
  }, {
    "title": "Static rendering"
  }, {
    "title": "Session handling"
  }, {
    "title": "Secret management"
  }]
}, {
  "title": "Frontend / Clients",
  "topics": [{
    "title": "JavaScript"
  }, {
    "title": "CSS"
  }, {
    "title": "Tailwind CSS"
  }, {
    "title": "Images"
  }, {
    "title": "Responsive layout"
  }, {
    "title": "Module systems"
  }, {
    "title": "Libraries"
  }, {
    "title": "Lighthouse / Page speed"
  }]
}, {
  "title": "CDN / Static Assets",
  "topics": [{
    "title": "CloudFront"
  }, {
    "title": "Fingerprinting"
  }, {
    "title": "Cache invalidation"
  }, {
    "title": "Request logging with request IDs"
  }]
}, {
  "title": "Security",
  "topics": [{
    "title": "Handling Access Tokens"
  }, {
    "title": "CSP"
  }, {
    "title": "IAM"
  }, {
    "title": "Production access"
  }, {
    "title": "Network security"
  }, {
    "title": "Personal Identifiable Information (PII)"
  }, {
    "title": "Encryption at rest"
  }, {
    "title": "Record encryption"
  }, {
    "title": "AWS Accounts as security boundary"
  }]
}, {
  "title": "Analytics",
  "topics": [{
    "title": "Privacy first"
  }, {
    "title": "Service metrics"
  }, {
    "title": "User interaction metrics"
  }]
}, {
  "title": "Performance",
  "topics": [{
    "title": "Page speed"
  }, {
    "title": "Serverless performance"
  }, {
    "title": "Caching"
  }, {
    "title": "CloudFront"
  }]
}, {
  "title": "Networking",
  "topics": [{
    "title": "VPCs"
  }, {
    "title": "Regions"
  }, {
    "title": "Multi-AZ / Regional availability"
  }]
}, {
  "title": "Licensing",
  "topics": [{
    "title": "Licensing basics"
  }]
}, {
  "title": "Compliance",
  "topics": [{
    "title": "GDPR"
  }, {
    "title": "PCI"
  }]
}, {
  "title": "Customer Support",
  "topics": [{
    "title": "Tools for customer support (non-invasive)"
  }, {
    "title": "Feature Requests by customers"
  }]
}, {
  "title": "API",
  "tags": ["feature"],
  "topics": [{
    "title": "Rate Limiting"
  }, {
    "title": "Authentication"
  }, {
    "title": "Authorization"
  }, {
    "title": "API Docs"
  }, {
    "title": "Public vs Private API"
  }]
}, {
  "title": "Account Management",
  "tags": ["feature"],
  "topics": [{
    "title": "Account creation"
  }, {
    "title": "Verification flows"
  }, {
    "title": "Password flows"
  }, {
    "title": "Newsletter"
  }, {
    "title": "Account deletion"
  }, {
    "title": "Service Emails"
  }]
}, {
  "title": "Billing",
  "tags": ["feature"],
  "topics": [{
    "title": "How do you determine the price for a product?"
  }, {
    "title": "Stripe"
  }, {
    "title": "Credit Card Management"
  }, {
    "title": "Dunning"
  }, {
    "title": "VAT"
  }]
}, {
  "title": "Blog",
  "tags": ["feature"],
  "topics": [{
    "title": "Building a site generator"
  }]
}, {
  "title": "Documentation",
  "tags": ["feature"],
  "topics": [{
    "title": "Building a site generator"
  }]
}, {
  "title": "Teams / Orgs",
  "tags": ["feature"],
  "topics": [{
    "title": "Billing"
  }, {
    "title": "User identity"
  }, {
    "title": "Invitation flows"
  }]
}, {
  "title": "Landing Page",
  "tags": ["feature"],
  "topics": [{
    "title": "SEO"
  }, {
    "title": "Page Performance"
  }, {
    "title": "Page layout"
  }]
}]